qupyt/__init__.py
qupyt/gates.py
qupyt/layers.py
qupyt/qubit.py
qupyt/states.py
qupyt/subroutines.py
qupyt/algorithms/__init__.py
qupyt/algorithms/bernstein_vazirani.py
qupyt/algorithms/deutsch.py
qupyt/algorithms/deutsch_josza.py
qupyt/algorithms/grover.py
qupyt-0.1.3.dist-info/licenses/LICENSE
qupyt-0.1.3.dist-info/METADATA
qupyt-0.1.3.dist-info/WHEEL
qupyt-0.1.3.dist-info/top_level.txt
qupyt-0.1.3.dist-info/RECORD
